scanforwebcams/__init__.py
scanforwebcams/cams.json
scanforwebcams/cli.py
scanforwebcams/geoip.py
scanforwebcams/geoip_cache.json
scanforwebcams/search.py
scanforwebcams/tmp.py
scanforwebcams/universal.py
scan_for_webcams-1.4.3.dist-info/LICENSE
scan_for_webcams-1.4.3.dist-info/METADATA
scan_for_webcams-1.4.3.dist-info/WHEEL
scan_for_webcams-1.4.3.dist-info/entry_points.txt
scan_for_webcams-1.4.3.dist-info/top_level.txt
scan_for_webcams-1.4.3.dist-info/RECORD
