Metadata-Version: 2.1
Name: scan-for-webcams
Version: 1.4.3
Summary: UNKNOWN
Home-page: https://github.com/JettChenT/scan-for-webcams
Author: Jett Chen
Author-email: contact@jettchen.me
License: MIT
Platform: UNKNOWN
Requires-Dist: shodan
Requires-Dist: requests
Requires-Dist: rich
Requires-Dist: pillow
Requires-Dist: clarifai
Requires-Dist: halo
Requires-Dist: fire
Requires-Dist: python-dotenv
Requires-Dist: pycountry
